{
  "kind": "collectionType",
  "collectionName": "doctors",
  "info": {
    "singularName": "doctor",
    "pluralName": "doctors",
    "displayName": "Doctor"
  },
  "options": {
    "draftAndPublish": true
  },
  "pluginOptions": {},
  "attributes": {
    "Name": {
      "type": "string"
    },
    "Address": {
      "type": "string"
    },
    "Patients": {
      "type": "string"
    },
    "Year_of_Experience": {
      "type": "string"
    },
    "StartTime": {
      "type": "time"
    },
    "EndTime": {
      "type": "time"
    },
    "About": {
      "type": "blocks"
    },
    "category": {
      "type": "relation",
      "relation": "manyToOne",
      "target": "api::category.category",
      "inversedBy": "doctors"
    },
    "Phone": {
      "type": "string"
    },
    "image": {
      "allowedTypes": [
        "images",
        "files",
        "videos",
        "audios"
      ],
      "type": "media",
      "multiple": true
    },
    "Premium": {
      "type": "boolean"
    }
  }
}
